spine_items/__init__.py
spine_items/animations.py
spine_items/commands.py
spine_items/database_validation.py
spine_items/db_writer_executable_item_base.py
spine_items/db_writer_item_base.py
spine_items/models.py
spine_items/resources_icons_rc.py
spine_items/utils.py
spine_items/version.py
spine_items/widgets.py
spine_items/data_connection/__init__.py
spine_items/data_connection/commands.py
spine_items/data_connection/custom_file_system_watcher.py
spine_items/data_connection/data_connection.py
spine_items/data_connection/data_connection_factory.py
spine_items/data_connection/data_connection_icon.py
spine_items/data_connection/executable_item.py
spine_items/data_connection/item_info.py
spine_items/data_connection/output_resources.py
spine_items/data_connection/utils.py
spine_items/data_connection/ui/__init__.py
spine_items/data_connection/ui/data_connection_properties.py
spine_items/data_connection/ui/data_connection_properties.ui
spine_items/data_connection/ui/file_pattern_dialog.py
spine_items/data_connection/ui/file_pattern_dialog.ui
spine_items/data_connection/widgets/__init__.py
spine_items/data_connection/widgets/add_data_connection_widget.py
spine_items/data_connection/widgets/custom_menus.py
spine_items/data_connection/widgets/data_connection_properties_widget.py
spine_items/data_connection/widgets/file_pattern_dialog.py
spine_items/data_store/__init__.py
spine_items/data_store/commands.py
spine_items/data_store/data_store.py
spine_items/data_store/data_store_factory.py
spine_items/data_store/data_store_icon.py
spine_items/data_store/executable_item.py
spine_items/data_store/item_info.py
spine_items/data_store/output_resources.py
spine_items/data_store/ui/__init__.py
spine_items/data_store/ui/data_store_properties.py
spine_items/data_store/ui/data_store_properties.ui
spine_items/data_store/widgets/__init__.py
spine_items/data_store/widgets/add_data_store_widget.py
spine_items/data_store/widgets/data_store_properties_widget.py
spine_items-0.24.3.dist-info/licenses/COPYING
spine_items-0.24.3.dist-info/licenses/COPYING.LESSER
spine_items-0.24.3.dist-info/METADATA
spine_items-0.24.3.dist-info/WHEEL
spine_items-0.24.3.dist-info/top_level.txt
spine_items-0.24.3.dist-info/RECORD
