Metadata-Version: 2.4
Name: spine_items
Version: 0.24.3
Summary: Spine project items
Author: contributors
Author-email: Spine Project consortium <spine_info@vtt.fi>
License: LGPL-3.0-or-later
Project-URL: Repository, https://github.com/spine-tools/spine-items
Project-URL: Issues, https://github.com/spine-tools/Spine-Toolbox/issues
Project-URL: Changelog, https://github.com/spine-tools/Spine-Toolbox/blob/master/CHANGELOG.md
Keywords: energy system modelling,workflow,optimisation,database
Classifier: Programming Language :: Python :: 3
Classifier: License :: OSI Approved :: GNU Lesser General Public License v3 (LGPLv3)
Classifier: Operating System :: OS Independent
Requires-Python: >=3.10
License-File: COPYING
License-File: COPYING.LESSER
Requires-Dist: spinedb_api>=0.36.2
Requires-Dist: spine_engine>=0.26.3
Dynamic: license-file
